{"1000":"ICROESMMXXX","1457":"LLISESM1XXX","1460":"CRESESMMXXX","1465":"INGDESMMXXX","1474":"CITIESMXSEC","1479":"NATXESMMXXX","1480":"VOWAES22XXX","1485":"BOFAES2XXXX","1488":"PICTESMMXXX","1490":"SELFESMMXXX","1491":"TRIOESMMXXX","1494":"BCITESMMXXX","1497":"ESSIESMMXXX","1508":"RCINESM1XXX","1525":"BCDMESMMXXX","1538":"ICBKESMMXXX","1541":"BCMAESMMTGT","1544":"BACAESMMXXX","1545":"AGRIESMMXXX","1547":"LOCYESMMNDP","1553":"PCBCESBBXXX","1563":"NTSBESM1XXX","1569":"IGSEESMMXXX","1575":"WUIBESM2XXX","1578":"SOBKESM2XXX","1583":"REVOESM2XXX","2000":"CECAESMMXXX","2045":"CECAESMM045","2056":"CECAESMM056","2080":"CAGLESMMVIG","2085":"CAZRES2ZXXX","2095":"BASKES2BXXX","2100":"CAIXESBBXXX","2103":"UCJAES2MXXX","3001":"CJALESSSXXX","3005":"BCOEESMM005","3008":"BCOEESMM008","3009":"BCOEESMM009","3017":"BCOEESMM017","3023":"BCOEESMM023","3025":"CDENESBBXXX","3035":"CLPEES2MXXX","3058":"CCRIES2AXXX","3059":"BCOEESMM059","3060":"BCOEESMM060","3067":"BCOEESMM067","3076":"BCOEESMM076","3080":"BCOEESMM080","3081":"ERSVES22XXX","3085":"BCOEESMM085","3140":"CGUIESBAXXX","3159":"BCOEESMM159","3183":"CASDESBBXXX","3187":"BCOEESMM187","3190":"BCOEESMM190","3191":"BCOEESMM191","A06302657":"MRTFESM2XXX","0220":"FIOFESM1XXX","0224":"SCFBESMMXXX","0229":"POPLESMMXXX","0232":"INVLESMMXXX","0234":"CCOCESMMXXX","0237":"CSURES2CXXX","0219":"BMCEESMMXXX","0011":"ALLFESMMXXX","0019":"DEUTESBBASS","0036":"SABNESMMXXX","0038":"BSSSESM2XXX","0049":"BSCHESMMXXX","0061":"BMARES2MXXX","0073":"OPENESMMXXX","0078":"BAPUES22XXX","0081":"BSABESBBXXX","0083":"RENBESMMXXX","0108":"SOGEESMMXXX","0128":"BKBKESMMXXX","0136":"AREBESMMXXX","0149":"BNPAESMHXXX","0151":"CHASESM3XXX","0152":"BPLCESMMXXX","0154":"BSUIESMMXXX","0159":"COBAESMXMCA","0162":"MIDLESMXXXX","0169":"NACNESMMXXX","0182":"BBVAESMMXXX","0186":"BFIVESBBXXX","0188":"ALCLESMMXXX","0198":"BCOEESMMXXX","0200":"DEGRESBBXXX","0211":"PROAESMMXXX","0218":"FCEFESM1XXX","A79192258":"CRESESM2XXX","W0075543I":"MSTAESM1XXX","0239":"EVOBESMMXXX","0240":"BCCAESMMXXX","0241":"AYGBESMMXXX"}